MANIFEST.in
README.md
README.rst
setup.cfg
setup.py
app/__init__.py
app/manager.py
app/utils.py
docker_volume_manager.egg-info/PKG-INFO
docker_volume_manager.egg-info/SOURCES.txt
docker_volume_manager.egg-info/dependency_links.txt
docker_volume_manager.egg-info/entry_points.txt
docker_volume_manager.egg-info/not-zip-safe
docker_volume_manager.egg-info/requires.txt
docker_volume_manager.egg-info/top_level.txt