Metadata-Version: 1.1
Name: docker-volume-manager
Version: 1.0.2
Summary: Convenient cli app for docker volume management.
Home-page: UNKNOWN
Author: Ankur Srivastava
Author-email: UNKNOWN
License: MIT
Download-URL: https://github.com/ansrivas/docker-volume-manager/archive/1.0.0.tar.gz
Platform: UNKNOWN
Classifier: Programming Language :: Python :: 2
Classifier: Programming Language :: Python :: 2.7
Classifier: Programming Language :: Python :: 3
Classifier: Programming Language :: Python :: 3.4
Classifier: Programming Language :: Python :: 3.5
Classifier: Programming Language :: Python :: 3.6
